{
  "parent": "candlelight:main/place_stove",
  "criteria": {
    "cooking_pot": {
      "conditions": {
        "location": [
          {
            "block": "candlelight:cooking_pot",
            "condition": "minecraft:block_state_property"
          }
        ]
      },
      "trigger": "minecraft:placed_block"
    }
  },
  "display": {
    "announce_to_chat": true,
    "description": {
      "translate": "candlelight.advancement.cooking_pot.desc"
    },
    "frame": "task",
    "hidden": false,
    "icon": {
      "item": "candlelight:cooking_pot"
    },
    "show_toast": true,
    "title": {
      "translate": "candlelight.advancement.cooking_pot"
    }
  },
  "requirements": [
    [
      "cooking_pot"
    ]
  ],
  "sends_telemetry_event": true
}